setup.cfg
setup.py
bin/hostsctl
hostsctl/__init__.py
hostsctl/core.py
hostsctl/entries.py
hostsctl.egg-info/PKG-INFO
hostsctl.egg-info/SOURCES.txt
hostsctl.egg-info/dependency_links.txt
hostsctl.egg-info/top_level.txt