Metadata-Version: 1.0
Name: hostsctl
Version: 0.0.1
Summary: The hosts file manipulator
Home-page: https://github.com/j-mak/hostman
Author: Jozef "sunny" Mak
Author-email: sunny@jozefmak.eu
License: MIT License
Keywords: hosts
Platform: UNKNOWN
